virtualitics_cli/__init__.py
virtualitics_cli/virtualitics_cli.py
virtualitics_cli-1.37.0.dist-info/METADATA
virtualitics_cli-1.37.0.dist-info/WHEEL
virtualitics_cli-1.37.0.dist-info/entry_points.txt
virtualitics_cli-1.37.0.dist-info/RECORD
