Metadata-Version: 2.4
Name: virtualitics-cli
Version: 1.37.0
Summary: A command line interface for initializing, packaging, and deploying Custom Apps to the Virtualitics AI Platform from a local development environment.
License: MIT
Author: Virtualitics Engineering
Author-email: engineering@virtualitics.com
Requires-Python: >=3.11,<3.12
Classifier: License :: OSI Approved :: MIT License
Classifier: Operating System :: MacOS :: MacOS X
Classifier: Operating System :: Microsoft :: Windows :: Windows 10
Classifier: Operating System :: POSIX
Classifier: Programming Language :: Python :: 3
Classifier: Programming Language :: Python :: 3.11
Requires-Dist: art (>=6.1,<7.0)
Requires-Dist: build (>=1.2.1,<2.0.0)
Requires-Dist: requests (>=2.31.0,<3.0.0)
Requires-Dist: typer (>=0.19.2,<0.20.0)
